<?xml version="1.0" encoding="UTF-8"?>
<PSILive><General LeagueID="323" HomeTeamID="179905" HomeName="Denver" AwayTeamID="179904" AwayName="Chicago"><Settings ForwardTime="no"><PeriodLengths P1="15" P2="15" P3="15" P4="15" OT1="10" OT2="10" OT3="10" OT4="10" OT5="10"/></Settings></General><Summary><Score Home="11" Away="13"/><Home Name=""><Period Num="1" G="0" S="0" PIM="0"/></Home><Away Name=""><Period Num="1" G="0" S="0" PIM="0"/></Away></Summary><GameState realtime="0" Status="Final" Period="1" Time="0"><streammessage/><CurrentState Name="Even Strength"/></GameState><HomeTeam><Player PlayerID="2663996" Name="Brendan Mundorf" Number="2" Pos="A" G="3" A="0" SOG="5" PIM="0" PLUS="0"/><Player PlayerID="2666653" Name="Brian Langtry" Number="6" Pos="M" G="2" A="0" SOG="3" PIM="0" PLUS="0"/><Player PlayerID="2712052" Name="Greg Downing" Number="8" Pos="M" G="0" A="0" SOG="2" PIM="0" PLUS="0"/><Player PlayerID="2664006" Name="Mike Ward" Number="9" Pos="M" G="0" A="0" SOG="0" PIM="0" PLUS="0"/><Player PlayerID="2712050" Name="Matt Bocklet" Number="10" Pos="D" G="0" A="0" SOG="0" PIM=".5" PLUS="0"/><Player PlayerID="2663999" Name="Drew Westervelt" Number="14" Pos="A" G="2" A="1" SOG="6" PIM="0" PLUS="0"/><Player PlayerID="2663991" Name="Jeff Sonke" Number="15" Pos="M" G="0" A="0" SOG="3" PIM="0" PLUS="0"/><Player PlayerID="2663984" Name="Matt Brown" Number="16" Pos="A" G="0" A="1" SOG="1" PIM="0" PLUS="0"/><Player PlayerID="2663986" Name="Tom Ethington" Number="17" Pos="D" G="0" A="0" SOG="0" PIM=".5" PLUS="0"/><Player PlayerID="2712054" Name="Kyle Harrison" Number="18" Pos="M" G="2" A="0" SOG="5" PIM="0" PLUS="0"/><Player PlayerID="2712056" Name="Sean Lindsay" Number="21" Pos="M" G="1" A="0" SOG="2" PIM="0" PLUS="0"/><Player PlayerID="2712051" Name="Jim Borell" Number="23" Pos="M" G="0" A="0" SOG="1" PIM="0" PLUS="0"/><Player PlayerID="2663983" Name="Lou Braun" Number="27" Pos="FO" G="0" A="0" SOG="0" PIM="0" PLUS="0"/><Player PlayerID="2663992" Name="Lee Zink" Number="29" Pos="D" G="0" A="0" SOG="0" PIM=".5" PLUS="0"/><Player PlayerID="2663998" Name="Thomas Garvey" Number="34" Pos="D" G="0" A="0" SOG="0" PIM="0" PLUS="0"/><Player PlayerID="2663994" Name="Nate Watkins" Number="35" Pos="M" G="1" A="0" SOG="2" PIM=".5" PLUS="0"/><Player PlayerID="2712057" Name="Eric Martin" Number="71" Pos="D" G="0" A="0" SOG="1" PIM="1" PLUS="0"/><Goalie PlayerID="2664000" Name="Jesse Schwartzman" Number="19" Pos="G" SA="21" GA="12" SAV="9" InNet="No" PIM="0" Type="" Minutes="0"/></HomeTeam><AwayTeam><Player PlayerID="2825663" Name="Brendan Loftus" Number="1" Pos="M" G="0" A="0" SOG="0" PIM="0" PLUS="0"/><Player PlayerID="2712031" Name="Liam Banks" Number="2" Pos="A" G="1" A="1" SOG="4" PIM="1" PLUS="0"/><Player PlayerID="2713052" Name="Tim Booth" Number="5" Pos="M" G="0" A="0" SOG="0" PIM="0" PLUS="0"/><Player PlayerID="2663979" Name="Brendan Cannon" Number="7" Pos="A" G="0" A="0" SOG="0" PIM="0" PLUS="0"/><Player PlayerID="2663977" Name="Terry Kimener" Number="16" Pos="M" G="0" A="2" SOG="2" PIM="0" PLUS="0"/><Player PlayerID="2663964" Name="Jake Deane" Number="17" Pos="D" G="1" A="1" SOG="1" PIM="0" PLUS="0"/><Player PlayerID="2663961" Name="Kevin Leveille" Number="19" Pos="A" G="3" A="0" SOG="4" PIM="0" PLUS="0"/><Player PlayerID="2663982" Name="John Carrozza" Number="21" Pos="M" G="0" A="0" SOG="0" PIM="0" PLUS="0"/><Player PlayerID="2712037" Name="Steven Holmes" Number="23" Pos="D" G="0" A="0" SOG="0" PIM="3" PLUS="0"/><Player PlayerID="2663968" Name="Steve Whittenberg" Number="24" Pos="D" G="0" A="0" SOG="1" PIM="0" PLUS="0"/><Player PlayerID="2712041" Name="Chris Rotelli" Number="25" Pos="M" G="1" A="0" SOG="1" PIM="0" PLUS="0"/><Player PlayerID="2712032" Name="Greg Bice" Number="27" Pos="D" G="0" A="0" SOG="0" PIM="0" PLUS="0"/><Player PlayerID="2712034" Name="DJ Driscoll" Number="31" Pos="D" G="0" A="0" SOG="1" PIM="0" PLUS="0"/><Player PlayerID="2712038" Name="Anthony Kelly" Number="34" Pos="FO" G="0" A="0" SOG="0" PIM="0" PLUS="0"/><Player PlayerID="2663976" Name="Steven Brooks" Number="44" Pos="M" G="2" A="0" SOG="2" PIM="0" PLUS="0"/><Player PlayerID="2712048" Name="Matt Striebel" Number="45" Pos="M" G="2" A="2" SOG="3" PIM="0" PLUS="0"/><Player PlayerID="2666634" Name="Mike Leveille" Number="91" Pos="A" G="2" A="0" SOG="2" PIM="0" PLUS="0"/><Goalie PlayerID="2663960" Name="Mike Gabel" Number="9" Pos="G" SA="31" GA="11" SAV="20" InNet="No" PIM="0" Type="" Minutes="0"/></AwayTeam><PlayByPlay><Period Num="1"/></PlayByPlay></PSILive>
